{
  "url": "https://www.elektromarketim.com/hims-emef-22t2-ss-20-siyah-soketli-22kw-siyah-20m-elektrikli-arac-sarj-kablosu",
  "sku": "EMEF-22T2-SS-20",
  "title": "Hims EMEF-22T2-SS-20 Siyah Soketli 22kW Siyah 20m Elektrikli Araç Şarj Kablosu",
  "fullDescription": "Hims Tip 2 Araç Şarj Kablosu 22kW Destekli Siyah 20 Metre Türkiye'de üretilen tüm elektrikli araçlar ile uyumludur. 22kW araç şarj kablosu hem Avrupa hem de Türkiye'deki t üm tip 2 soketler ile kullanıma uygundur. Düz yapıya sahip Hims araç şarj kablosu, rahatlıkla her yere taşınabilir ve kullanılabilir. Yüksek akım taşımaya uygun özelliklere sahip gümüş kablo kontakları, yalnızca yüksek performanslı iletkenlik sağlamakla kalmaz, aynı zamanda ısınmanın önüne geçerek şarj cihazlarının ve aracın güvenliğini de garanti altına alır. Not: Hims markasının şarj kablosu garantisi, teslim edildikten sonra başlar ve 2 yıl geçerlidir. Ürünün bütün parçaları dahil olmak üzere tamamı garanti kapsamındadır. Garanti kapsamında işçilik ve üretim hatalarına karşı garanti mevcuttur. Geleceğin enerjisine yatırım yapmaya hazır mısınız? Elektrikli araç altyapısına yaptığınız yatırımla hem çevreyi koruyun hem de büyüyen bir pazarda yerinizi alın. Bayilik programımız için tıklayın , yerli üretimimiz olan şarj istasyonu ve kabloları ile geleceğin dönüşümüne ortak olun! Elektrikli Araç Şarj Kablosu Özelliği Nedir? Elektrikli araç şarj kablosu modelleri genel olarak istasyondan ayrı olarak da üretilmektedir. Hem yedek kablo olarak hem de kablosu olmayan elektrikli araç şarj istasyonları için kullanım sunarlar. Yapıları bakımından yüksek performans sunan elektrikli araç şarj kablosu modelleri, en iyi şekilde aracınızı şarj etmenize yardımcı olmaktadır. Elektrikli Araç Şarj Kablosu Kullanım Alanları Nedir? Elektrikli araç şarj kablosu modeli uygun olan elektrikli araç şarj istasyonu ile kullanılmaktadır. Uygun teknik özelliklerde olduğuna dikkat ederek seçim yapabilirsiniz. Ülke olarak Türkiye ve Avrupa kullanabilen soketleri bulunması ile oldukça kullanışlıdır. Pek çok elektrikli araç şarj istasyonu ile uyumlu şekilde çalışmaktadır. Elektrikli Araç Şarj Kablosu Nasıl Seçilir? Elektrikli araç şarj kablosu teknik özellikleri doğrultusunda uyumluluğuna bakılarak seçilmektedir. Güç olarak elektrikli araç şarj istasyonu ile uyumlu çalışıyorsa o zaman elektrikli araç şarj kablosu seçimi kolaylıkla yapılabilmektedir. Ürün Özellikleri Çalışma Akımı : 32A Güç Aktarım Kapasitesi : 22 kW Çalıma Gerilimi : 380V AC ( Trifaze ) (Trifaze kablolar, Monofaze sistemlerde kullanım için uygundur.) Çalışma Frekansı : 50/60 Hz Çalışma Sıcaklığı : -25 ile 55 derece Nem : %95'e kadar yoğuşmasız Kontak Kaplama : Gümüş İletken : %100 Bakır Depolama Sıcaklığı : -30 ile 80 derece Ürün Kablo Uzunluğu : 20 metre Ürün Kablo Kesiti : 5x6 Teknik Özellikler Kablo Uzunluğu : 20 m Kablo Rengi : Siyah Ortalama Puan ★★★★★ Çok İyi ★★★★ ★ İyi ★★★ ★★ Ortalama ★★ ★★★ Kötü ★ ★★★★ Çok Kötü ( ) ( ) ( ) ( ) ( ) PRODUCT_DATA.push(JSON.parse('{\\\"id\\\":\\\"115125\\\",\\\"name\\\":\\\"Hims EMEF-22T2-SS-20 22kW Tip 2 Siyah Soketli 20m Elektrikli Ara\\\\u00e7 \\\\u015earj Kablosu\\\",\\\"code\\\":\\\"TP178441\\\",\\\"supplier_code\\\":\\\"EMEF-22T2-SS-20\\\",\\\"sale_price\\\":\\\"15818.4\\\",\\\"total_base_price\\\":29203.2,\\\"total_sale_price\\\":18982.08,\\\"vat\\\":20,\\\"subproduct_code\\\":\\\"\\\",\\\"subproduct_id\\\":0,\\\"price\\\":24336,\\\"total_price\\\":29203.2,\\\"available\\\":true,\\\"category_ids\\\":\\\"4885\\\",\\\"barcode\\\":\\\"8684556329536\\\",\\\"subproduct_name\\\":\\\"\\\",\\\"image\\\":\\\"https:\\\\/\\\\/www.elektromarketim.com\\\\/hims-emef-22t2-ss-20-siyah-soketli-22kw-siyah-20m-elektrikli-arac-sarj-kablosu-elektrikli-arac-sarj-kablolari-hims-519607-11-O.jpg\\\",\\\"quantity\\\":9999,\\\"url\\\":\\\"hims-emef-22t2-ss-20-siyah-soketli-22kw-siyah-20m-elektrikli-arac-sarj-kablosu\\\",\\\"currency\\\":\\\"TL\\\",\\\"currency_target\\\":\\\"TL\\\",\\\"brand\\\":\\\"Hims\\\",\\\"category\\\":\\\"Elektrikli Ara\\\\u00e7 \\\\u015earj Kablolar\\\\u0131\\\",\\\"category_id\\\":\\\"4885\\\",\\\"category_path\\\":\\\"Elektrikli Ara\\\\u00e7 \\\\u015earj \\\\u0130stasyonlar\\\\u0131 ve Ekipmanlar\\\\u0131 > \\\",\\\"model\\\":\\\"\\\",\\\"personalization_id\\\":0,\\\"variant1\\\"",
  "specifications": {
    "Çalışma Akımı": "32A",
    "Güç Aktarım Kapasitesi": "22 kW",
    "Çalıma Gerilimi": "380V AC ( Trifaze ) (Trifaze kablolar, Monofaze sistemlerde kullanım için uygundur.)",
    "Çalışma Frekansı": "50/60 Hz",
    "Çalışma Sıcaklığı": "-25 ile 55 derece",
    "Nem": "%95'e kadar yoğuşmasız",
    "Kontak Kaplama": "Gümüş",
    "İletken": "%100 Bakır",
    "Depolama Sıcaklığı": "-30 ile 80 derece",
    "Ürün Kablo Uzunluğu": "20 metre",
    "Ürün Kablo Kesiti": "5x6",
    "Kablo Uzunluğu": "20 m",
    "Kablo Rengi": "Siyah"
  },
  "features": []
}