{
  "url": "https://www.elektromarketim.com/hims-emef-22t2-ss-16-siyah-soketli-22kw-siyah-16m-elektrikli-arac-sarj-kablosu",
  "sku": "EMEF-22T2-SS-16",
  "title": "Hims EMEF-22T2-SS-16 Siyah Soketli 22kW Siyah 16m Elektrikli Araç Şarj Kablosu",
  "fullDescription": "Hims 22kw Destekli Siyah 16 Metre Elektrikli Araç Şarj Kablosu Türkiye'de üretilen tüm elektrikli araçlar ile uyumludur. 22kW araç şarj kablosu hem Avrupa hem de Türkiye'deki t üm tip 2 soketler ile kullanıma uygundur. Düz yapıya sahip Hims şarj kablosu, rahatlıkla her yere taşınabilir ve kullanılabilir. Yüksek akım taşımaya uygun özelliklere sahip gümüş kablo kontakları, yalnızca yüksek performanslı iletkenlik sağlamakla kalmaz, aynı zamanda ısınmanın önüne geçerek şarj cihazlarının ve aracın güvenliğini de garanti altına alır. Not: Hims markasının şarj kablosu garantisi, teslim edildikten sonra başlar ve 2 yıl geçerlidir. Ürünün bütün parçaları dahil olmak üzere tamamı garanti kapsamındadır. Garanti kapsamında işçilik ve üretim hatalarına karşı garanti mevcuttur. Geleceğin enerjisine yatırım yapmaya hazır mısınız? Elektrikli araç altyapısına yaptığınız yatırımla hem çevreyi koruyun hem de büyüyen bir pazarda yerinizi alın. Bayilik programımız için tıklayın , yerli üretimimiz olan şarj istasyonu ve kabloları ile geleceğin dönüşümüne ortak olun! Elektrikli Araç Şarj Kablosu Özelliği Nedir? Elektrikli araç şarj kablosu modelleri genel olarak istasyondan ayrı olarak da üretilmektedir. Hem yedek kablo olarak hem de kablosu olmayan elektrikli araç şarj istasyonları için kullanım sunarlar. Yapıları bakımından yüksek performans sunan elektrikli araç şarj kablosu modelleri, en iyi şekilde aracınızı şarj etmenize yardımcı olmaktadır. Elektrikli Araç Şarj Kablosu Kullanım Alanları Nedir? Elektrikli araç şarj kablosu modeli uygun olan elektrikli araç şarj istasyonu ile kullanılmaktadır. Uygun teknik özelliklerde olduğuna dikkat ederek seçim yapabilirsiniz. Ülke olarak Türkiye ve Avrupa kullanabilen soketleri bulunması ile oldukça kullanışlıdır. Pek çok elektrikli araç şarj istasyonu ile uyumlu şekilde çalışmaktadır. Elektrikli Araç Şarj Kablosu Nasıl Seçilir? Elektrikli araç şarj kablosu teknik özellikleri doğrultusunda uyumluluğuna bakılarak seçilmektedir. Güç olarak elektrikli araç şarj istasyonu ile uyumlu çalışıyorsa o zaman elektrikli araç şarj kablosu seçimi kolaylıkla yapılabilmektedir. Ürün Özellikleri Çalışma Akımı : 32A Güç Aktarım Kapasitesi : 22 kW Çalıma Gerilimi : 380V AC ( Trifaze ) (Trifaze kablolar, Monofaze sistemlerde kullanım için uygundur.) Çalışma Frekansı : 50/60 Hz Çalışma Sıcaklığı : -25 ile 55 derece Nem : %95'e kadar yoğuşmasız Kontak Kaplama : Gümüş İletken : %100 Bakır Depolama Sıcaklığı : -30 ile 80 derece Ürün Kablo Uzunluğu : 16 metre Ürün Kablo Kesiti : 5x6 Teknik Özellikler Kablo Rengi : Siyah Kablo Uzunluğu : 16 m Ortalama Puan ★★★★★ Çok İyi ★★★★ ★ İyi ★★★ ★★ Ortalama ★★ ★★★ Kötü ★ ★★★★ Çok Kötü ( ) ( ) ( ) ( ) ( ) {\"@context\":\"https:\\/\\/ \",\"@type\":\"Product\",\"name\":\"Hims EMEF-22T2-SS-16 22kW Tip 2 Siyah Soketli 16m Elektrikli Araç Şarj Kablosu\",\"image\":[\"https:\\/\\/www.elektromarketim.com\\/hims-emef-22t2-ss-16-siyah-soketli-22kw-siyah-16m-elektrikli-arac-sarj-kablosu-elektrikli-arac-sarj-kablolari-hims-519614-11-O.jpg\",\"https:\\/\\/www.elektromarketim.com\\/hims-emef-22t2-ss-16-siyah-soketli-22kw-siyah-16m-elektrikli-arac-sarj-kablosu-elektrikli-arac-sarj-kablolari-hims-519971-11-O.jpg\",\"https:\\/\\/www.elektromarketim.com\\/hims-emef-22t2-ss-16-siyah-soketli-22kw-siyah-16m-elektrikli-arac-sarj-kablosu-elektrikli-arac-sarj-kablolari-hims-519973-11-O.jpg\",\"https:\\/\\/www.elektromarketim.com\\/hims-emef-22t2-ss-16-siyah-soketli-22kw-siyah-16m-elektrikli-arac-sarj-kablosu-elektrikli-arac-sarj-kablolari-hims-519974-11-O.jpg\",\"https:\\/\\/www.elektromarketim.com\\/hims-emef-22t2-ss-16-siyah-soketli-22kw-siyah-16m-elektrikli-arac-sarj-kablosu-elektrikli-arac-sarj-kablolari-hims-519972-11-O.jpg\"],\"description\":\"\\n\\n\\nHims 22kw Destekli Siyah 16 Metre Elektrikli Araç Şarj Kablosu\\n\\n\\n\\nTürkiye\\\\'de üretilen tüm elektrikli araçlar ile uyumludur.\\n\\n22kW araç şarj kablosu hem Avrupa hem de Türkiye\\\\'deki tüm tip 2 soketler ile kullanıma uygundur.\\n\\n\\n\\nDüz yapıya sahip Hims şarj kablosu, rahatlıkla her yere taşınabilir ve kullanılabilir.Yüksek akım taşımaya uygun özelliklere sahip gümüş kablo kontakları, yalnızca yüksek performanslı iletkenlik sağlamakla kalmaz, aynı zamanda ısınmanın önüne geçerek şarj cihazlarının ve aracın güvenliğini de garanti altına alır.Not: Hims markasının şarj kablosu garantisi, teslim edildikten sonra başlar ve 2 yıl geçerlidir. Ürünün bütün parçaları dahil olmak üzere tamamı garanti kapsamındadır. Garanti kapsamında işçilik ve üretim hatalarına karşı garanti mevcuttur.\\nGeleceğin enerjisine yatırım yapmaya hazır mısınız? Elektrikli araç altyapısına yaptığınız yatırımla hem çevreyi koruyun hem de büyüyen bir pazarda yerinizi alın. Bayilik programımız için tıklayın, yerli üretimimiz olan şarj istasyonu ve kabloları ile geleceğin dönüşümüne ortak olun!\\n\\n\\n\\nElektrikli Araç Şarj Kablosu Özelliği Nedir?\\n\\n\\n\\nElektrikli araç şarj kablosu modelleri genel olarak istasyondan ayrı olarak da üretilmektedir. Hem yedek kablo olarak hem de kablosu olmayan elektrikli araç şarj istasyonları için kullanım sunarlar. Yapıları bakımından yüksek performans sunan elektrikli araç şarj kablosu modelleri, en iyi şekilde aracınızı şarj etmenize yardımcı olmaktadır.\\n\\n\\n\\n\\n\\nElektrikli Araç Şarj Kablosu Kullanım Alanları Nedir?\\n\\n\\n\\nElektrikli araç şarj kablosu modeli uygun olan elektrikli araç şarj istasyonu ile kullanılmaktadır. Uygun teknik özelliklerde olduğuna dikkat ederek seçim yapabilirsiniz. Ülke olarak Türkiye ve Avrupa kullanabilen soketleri bulunması ile oldukça kullanışlıdır. Pek çok elektrikli araç şarj istasyonu ile uyumlu şekilde çalışmaktadır.\\n\\n\\n\\n\\n\\nElektrikli Araç Şarj Kablosu Nasıl Seçilir?\\n\\n\\n\\nElektrikli araç şarj kablosu teknik özellikleri doğrultusunda uyumluluğuna bakılarak seçilmektedir. Güç olarak elektrikli araç şarj istasyonu ile uyumlu çalışıyorsa o zaman elektrikli araç şarj kablosu seçimi kolaylıkla yapılabilmektedir.\\n\\n\\n\\n\\n\\n\\nÜrün Özellikleri\\n\\n\\nÇalışma Akımı\\n:\\n32A\\n\\n\\nGüç Aktarım Kapasitesi\\n:\\n22 kW\\n\\n\\nÇalıma Gerilimi\\n:\\n…",
  "specifications": {
    "Çalışma Akımı": "32A",
    "Güç Aktarım Kapasitesi": "22 kW",
    "Çalıma Gerilimi": "380V AC ( Trifaze ) (Trifaze kablolar, Monofaze sistemlerde kullanım için uygundur.)",
    "Çalışma Frekansı": "50/60 Hz",
    "Çalışma Sıcaklığı": "-25 ile 55 derece",
    "Nem": "%95'e kadar yoğuşmasız",
    "Kontak Kaplama": "Gümüş",
    "İletken": "%100 Bakır",
    "Depolama Sıcaklığı": "-30 ile 80 derece",
    "Ürün Kablo Uzunluğu": "16 metre",
    "Ürün Kablo Kesiti": "5x6",
    "Kablo Rengi": "Siyah",
    "Kablo Uzunluğu": "16 m"
  },
  "features": []
}