{
  "url": "https://www.elektromarketim.com/hims-emef-22t2-tb-10-beyaz-soketli-22kw-turuncu-10m-elektrikli-arac-sarj-kablosu",
  "sku": "EMEF-22T2-TB-10",
  "title": "Hims EMEF-22T2-TB-10 22kW Destekli 10m Elektrikli Araç Şarj Kablosu",
  "fullDescription": "Hims 22kw Destekli Turuncu 10 Metre Elektrikli Araç Şarj Kablosu Türkiye'de üretilen tüm elektrikli araçlar ile uyumludur. 22kW araç şarj kablosu hem Avrupa hem de Türkiye'deki t üm tip 2 soketler ile kullanıma uygundur. Düz yapıya sahip Hims şarj kablosu, rahatlıkla her yere taşınabilir ve kullanılabilir. Yüksek akım taşımaya uygun özelliklere sahip gümüş kablo kontakları, yalnızca yüksek performanslı iletkenlik sağlamakla kalmaz, aynı zamanda ısınmanın önüne geçerek şarj cihazlarının ve aracın güvenliğini de garanti altına alır. Not: Hims markasının şarj kablosu garantisi, teslim edildikten sonra başlar ve 2 yıl geçerlidir. Ürünün bütün parçaları dahil olmak üzere tamamı garanti kapsamındadır. Garanti kapsamında işçilik ve üretim hatalarına karşı garanti mevcuttur. Geleceğin enerjisine yatırım yapmaya hazır mısınız? Elektrikli araç altyapısına yaptığınız yatırımla hem çevreyi koruyun hem de büyüyen bir pazarda yerinizi alın. Bayilik programımız için tıklayın , yerli üretimimiz olan şarj istasyonu ve kabloları ile geleceğin dönüşümüne ortak olun! Elektrikli Araç Şarj Kablosu Özelliği Nedir? Elektrikli araç şarj kablosu modelleri genel olarak istasyondan ayrı olarak da üretilmektedir. Hem yedek kablo olarak hem de kablosu olmayan elektrikli araç şarj istasyonları için kullanım sunarlar. Yapıları bakımından yüksek performans sunan elektrikli araç şarj kablosu modelleri, en iyi şekilde aracınızı şarj etmenize yardımcı olmaktadır. Elektrikli Araç Şarj Kablosu Kullanım Alanları Nedir? Elektrikli araç şarj kablosu modeli uygun olan elektrikli araç şarj istasyonu ile kullanılmaktadır. Uygun teknik özelliklerde olduğuna dikkat ederek seçim yapabilirsiniz. Ülke olarak Türkiye ve Avrupa kullanabilen soketleri bulunması ile oldukça kullanışlıdır. Pek çok elektrikli araç şarj istasyonu ile uyumlu şekilde çalışmaktadır. Elektrikli Araç Şarj Kablosu Nasıl Seçilir? Elektrikli araç şarj kablosu teknik özellikleri doğrultusunda uyumluluğuna bakılarak seçilmektedir. Güç olarak elektrikli araç şarj istasyonu ile uyumlu çalışıyorsa o zaman elektrikli araç şarj kablosu seçimi kolaylıkla yapılabilmektedir. Ürün Özellikleri Çalışma Akımı : 32A Güç Aktarım Kapasitesi : 22 kW Çalıma Gerilimi : 380V AC ( Trifaze ) (Trifaze kablolar, Monofaze sistemlerde kullanım için uygundur.) Çalışma Frekansı : 50/60 Hz Çalışma Sıcaklığı : -25 ile 55 derece Nem : %95'e kadar yoğuşmasız Kontak Kaplama : Gümüş İletken : %100 Bakır Depolama Sıcaklığı : -30 ile 80 derece Ürün Kablo Uzunluğu : 10 metre Ürün Kablo Kesiti : 5x6 Teknik Özellikler Kablo Rengi : Turuncu Kablo Uzunluğu : 10 m Ürün Etiketleri Hafta Sonu Fırsatları Ortalama Puan ★★★★★ Çok İyi ★★★★ ★ İyi ★★★ ★★ Ortalama ★★ ★★★ Kötü ★ ★★★★ Çok Kötü ( ) ( ) ( ) ( ) ( ) Tamamlayıcı Ürünler <li class=\"fl col-3 col-md-4 col-sm-6 col-",
  "specifications": {
    "Çalışma Akımı": "32A",
    "Güç Aktarım Kapasitesi": "22 kW",
    "Çalıma Gerilimi": "380V AC ( Trifaze ) (Trifaze kablolar, Monofaze sistemlerde kullanım için uygundur.)",
    "Çalışma Frekansı": "50/60 Hz",
    "Çalışma Sıcaklığı": "-25 ile 55 derece",
    "Nem": "%95'e kadar yoğuşmasız",
    "Kontak Kaplama": "Gümüş",
    "İletken": "%100 Bakır",
    "Depolama Sıcaklığı": "-30 ile 80 derece",
    "Ürün Kablo Uzunluğu": "10 metre",
    "Ürün Kablo Kesiti": "5x6",
    "Kablo Rengi": "Turuncu",
    "Kablo Uzunluğu": "10 m"
  },
  "features": []
}