{
  "url": "https://www.elektromarketim.com/hims-emef-11t2-ss-5-11kw-tip-2-siyah-soketli-5m-elektrikli-arac-sarj-kablosu",
  "sku": "EMEF-11T2-SS-5",
  "title": "Hims EMEF-11T2-SS-5 11kW Tip 2 Siyah Soketli 5m Elektrikli Araç Şarj Kablosu",
  "fullDescription": "Hims 11kW Tip 2 Gri 5 Metre Elektrikli Araç Şarj Kablosu Türkiye'de üretilen tüm elektrikli araçlar ile uyumludur. 11kW araç şarj kablosu hem Avrupa hem de Türkiye'deki t üm tip 2 soketler ile kullanıma uygundur. Sadece monofaze kullanımda 3.6kW'ı, trifaze kullanımda ise 11kW'a kadar desteklemektedir. Düz yapıya sahip Hims şarj kablosu, rahatlıkla her yere taşınabilir ve kullanılabilir. Yüksek akım taşımaya uygun özelliklere sahip gümüş kablo kontakları, yalnızca yüksek performanslı iletkenlik sağlamakla kalmaz, aynı zamanda ısınmanın önüne geçerek şarj cihazlarının ve aracın güvenliğini de garanti altına alır. Not: Hims markasının şarj kablosu garantisi, teslim edildikten sonra başlar ve 2 yıl geçerlidir. Ürünün bütün parçaları dahil olmak üzere tamamı garanti kapsamındadır. Garanti kapsamında işçilik ve üretim hatalarına karşı garanti mevcuttur. Geleceğin enerjisine yatırım yapmaya hazır mısınız? Elektrikli araç altyapısına yaptığınız yatırımla hem çevreyi koruyun hem de büyüyen bir pazarda yerinizi alın. Bayilik programımız için tıklayın , yerli üretimimiz olan şarj istasyonu ve kabloları ile geleceğin dönüşümüne ortak olun! Elektrikli Araç Şarj Kablosu Özelliği Nedir? Elektrikli araç şarj kablosu modelleri genel olarak istasyondan ayrı olarak da üretilmektedir. Hem yedek kablo olarak hem de kablosu olmayan elektrikli araç şarj istasyonları için kullanım sunarlar. Yapıları bakımından yüksek performans sunan elektrikli araç şarj kablosu modelleri, en iyi şekilde aracınızı şarj etmenize yardımcı olmaktadır. Elektrikli Araç Şarj Kablosu Kullanım Alanları Nedir? Elektrikli araç şarj kablosu modeli uygun olan elektrikli araç şarj istasyonu ile kullanılmaktadır. Uygun teknik özelliklerde olduğuna dikkat ederek seçim yapabilirsiniz. Ülke olarak Türkiye ve Avrupa kullanabilen soketleri bulunması ile oldukça kullanışlıdır. Pek çok elektrikli araç şarj istasyonu ile uyumlu şekilde çalışmaktadır. Elektrikli Araç Şarj Kablosu Nasıl Seçilir? Elektrikli araç şarj kablosu teknik özellikleri doğrultusunda uyumluluğuna bakılarak seçilmektedir. Güç olarak elektrikli araç şarj istasyonu ile uyumlu çalışıyorsa o zaman elektrikli araç şarj kablosu seçimi kolaylıkla yapılabilmektedir. Ürün Özellikleri Çalışma Akımı : 20A Güç Aktarım Kapasitesi : 11 kW Çalıma Gerilimi : 480V AC Çalışma Frekansı : 50/60 Hz Çalışma Sıcaklığı : -30 ile 55 derece Nem : %5 - %95 bağıl nem Kontak Kaplama : Gümüş İletken : %100 Bakır Depolama Sıcaklığı : -40 °C...70 °C Ürün Kablo Uzunluğu : 5 metre Ürün Kablo Kesiti : 5x2.5+1x0.5 mm Teknik Özellikler Kablo Rengi : Siyah Kablo Uzunluğu : 5 m Ortalama Puan ★★★★★ Çok İyi ★★★★ ★ İyi ★★★ ★★ Ortalama ★★ ★★★ Kötü ★ ★★★★ Çok Kötü ( ) ( ) ( ) ( ) ( ) PRODUCT_DATA.push(JSON.parse('{\\\"id\\\":\\\"115625\\\",\\\"name\\\":\\\"H\\\\u0131ms Emef-11t2-ss-5 11kw T\\\\u0131p 2 S\\\\u0131yah Soketl\\\\u0131 5m Elektr\\\\u0131kl\\\\u0131 Arac Sarj Kablosu\\\",\\\"code\\\":\\\"TP180381\\\",\\\"supplier_code\\\":\\\"EMEF-11T2-SS-5\\\",\\\"sale_price\\\":\\\"4022.2\\\",\\\"total_base_price\\\":7425.6,\\\"total_sale_price\\\":4826.64,\\\"vat\\\":20,\\\"subproduct_code\\\":\\\"\\\",\\\"subproduct_id\\\":0,\\\"price\\\":6188,\\\"total_price\\\":7425.6,\\\"available\\\":true,\\\"category_ids\\\":\\\"4885\\\",\\\"barcode\\\":\\\"8684556329826\\\",\\\"subproduct",
  "specifications": {
    "Çalışma Akımı": "20A",
    "Güç Aktarım Kapasitesi": "11 kW",
    "Çalıma Gerilimi": "480V AC",
    "Çalışma Frekansı": "50/60 Hz",
    "Çalışma Sıcaklığı": "-30 ile 55 derece",
    "Kontak Kaplama": "Gümüş",
    "İletken": "%100 Bakır",
    "Ürün Kablo Uzunluğu": "5 metre",
    "Ürün Kablo Kesiti": "5x2.5+1x0.5 mm",
    "Kablo Rengi": "Siyah",
    "Kablo Uzunluğu": "5 m"
  },
  "features": []
}