{
  "url": "https://www.elektromarketim.com/hims-hcc-22t2-7-22kw-destekli-7m-elektrikli-arac-sarj-kablosu-115569",
  "sku": "HCC-22T2-7",
  "title": "Hims HCC-22T2-7 22kW Destekli 7m Elektrikli Araç Şarj Kablosu",
  "fullDescription": "Hims 22kw Destekli 7 Metre Elektrikli Araç Şarj Kablosu Hims bir elektromarketim markasıdır. Hims markasının üretmiş olduğu elektrikli araç şarj kablosudur. Aracınızı, Hims 7 metre elektirkli araç şarj kablosu ile tüm elektrikli araç şarj istasyonları ile güvenle şarj edebilirsiniz. 22kW araç şarj kablosu hem Avrupa hem de Türkiye'deki t üm tip 2 soketler ile kullanıma uygundur. Düz yapıya sahip Hims şarj kablosu, rahatlıkla her yere taşınabilir ve kullanılabilir. Yüksek akım taşımaya uygun özelliklere sahip gümüş kablo kontakları, yalnızca yüksek performanslı iletkenlik sağlamakla kalmaz, aynı zamanda ısınmanın önüne geçerek şarj cihazlarının ve aracın güvenliğini de garanti altına alır. Not: Hims markasının şarj kablosu garantisi, teslim edildikten sonra başlar ve 2 yıl geçerlidir. Ürünün bütün parçaları dahil olmak üzere tamamı garanti kapsamındadır. Garanti kapsamında işçilik ve üretim hatalarına karşı garanti mevcuttur. Not: Araç şarj kablosu, taşıma çantası ile birlikte gelir. Elektrikli Araç Şarj Kablosu Özelliği Nedir? Elektrikli araç şarj kablosu modelleri genel olarak istasyondan ayrı olarak da üretilmektedir. Hem yedek kablo olarak hem de kablosu olmayan elektrikli araç şarj istasyonları için kullanım sunarlar. Yapıları bakımından yüksek performans sunan elektrikli araç şarj kablosu modelleri, en iyi şekilde aracınızı şarj etmenize yardımcı olmaktadır. Teknik olarak elektrikli araç şarj istasyonunuz ile uyumlu ise Volti elektrikli araç şarj kablosu modelini tercih edebilirsiniz. Elektrikli Araç Şarj Kablosu Kullanım Alanları Nedir? Elektrikli araç şarj kablosu modeli uygun olan elektrikli araç şarj istasyonu ile kullanılmaktadır. Uygun teknik özelliklerde olduğuna dikkat ederek seçim yapabilirsiniz. Ülke olarak Türkiye ve Avrupa kullanabilen soketleri bulunması ile oldukça kullanışlıdır. Pek çok elektrikli araç şarj istasyonu ile uyumlu şekilde çalışmaktadır. Elektrikli Araç Şarj Kablosu Nasıl Seçilir? Elektrikli araç şarj kablosu teknik özellikleri doğrultusunda uyumluluğuna bakılarak seçilmektedir. Güç olarak elektrikli araç şarj istasyonu ile uyumlu çalışıyorsa o zaman elektrikli araç şarj kablosu seçimi kolaylıkla yapılabilmektedir. Ürün Özellikleri Çalışma Akımı : 32A Güç Aktarım Kapasitesi : 22 kW Çalıma Gerilimi : 380V AC Çalışma Frekansı : 50/60 Hz Çalışma Sıcaklığı : -25 ile 55 derece Nem : %95'e kadar yoğuşmasız Kontak Kaplama : Gümüş Depolama Sıcaklığı : -30 ile 80 derece Ürün Kablo Uzunluğu : 7 metre Ürün Kablo Kesiti : 5x6 Teknik Özellikler Kablo Rengi : Siyah Kablo Uzunluğu : 7 m Ortalama Puan ★★★★★ Çok İyi ★★★★ ★ İyi ★★★ ★★ Ortalama ★★ ★★★ Kötü ★ ★★★★ Çok Kötü ( ) ( ) ( ) ( ) ( ) const imgObserver = new IntersectionObserver((entries, self) => { entries.forEach(entry => { if (entry.isIntersecting) { lazyLoad(entry.target); self.unobserve(entry.target); } }); }); document.querySelectorAll('.lazy-picture').forEach((picture) => { imgObserver.observe(picture); }); $( document ).ready(function() { }); const lazyLoad = (picture) => { const sources = picture.querySelectorAll('source'); sources.forEach((source) => { if(source.dataset.srcset != undefined){ source.srcset = source.dataset.srcset; source.removeAttribute('data-srcset'); } }); } function onError() { this.onerror = null; fetch('https://cdnimg.elektromarketim.app/img', { method: 'POST', headers: { 'Content-Type': 'application/json'}, body: JSON.stringify({'u': this.parentNode.children[1].srcset}) }).then((response) => response.json()); console.log('HATA : '+ this.parentNode.children[0].srcset) if(this.parentNode != undefined){ if(this.getAttribute('data-src')){ this.parentNode.children[1] = this.getAttribute('data-src'); this.parentNode.children[0] = this.parentNode.children[1]; } else{ this.parentNode.children[1] = this.get",
  "specifications": {
    "Çalışma Akımı": "32A",
    "Güç Aktarım Kapasitesi": "22 kW",
    "Çalıma Gerilimi": "380V AC",
    "Çalışma Frekansı": "50/60 Hz",
    "Çalışma Sıcaklığı": "-25 ile 55 derece",
    "Nem": "%95'e kadar yoğuşmasız",
    "Kontak Kaplama": "Gümüş",
    "Depolama Sıcaklığı": "-30 ile 80 derece",
    "Ürün Kablo Uzunluğu": "7 metre",
    "Ürün Kablo Kesiti": "5x6",
    "Kablo Rengi": "Siyah",
    "Kablo Uzunluğu": "7 m"
  },
  "features": []
}